{
  "timestamp": "2025-03-25 16:45:42",
  "results": {
    "short": {
      "simple": [
        "jsw",
        "titan",
        "ADNA",
        "wipro",
        "ultratech",
        "infosys",
        "nestle",
        "Apollo",
        "bajaj",
        "asian",
        "icici",
        "ongc"
      ],
      "medium": [
        "jsw",
        "titan",
        "ADNA",
        "wipro",
        "ultratech",
        "infosys",
        "nestle",
        "Apollo",
        "bajaj",
        "asian",
        "icici",
        "ongc"
      ],
      "complex": [
        "jsw",
        "titan",
        "ADNA",
        "wipro",
        "ultratech",
        "infosys",
        "nestle",
        "Apollo",
        "bajaj",
        "asian",
        "icici",
        "ongc"
      ]
    },
    "medium": {
      "simple": [
        "jsw",
        "titan",
        "ADNA",
        "wipro",
        "ultratech",
        "infosys",
        "nestle",
        "Apollo",
        "bajaj",
        "asian",
        "icici",
        "ongc"
      ],
      "medium": [
        "jsw",
        "titan",
        "ADNA",
        "wipro",
        "ultratech",
        "infosys",
        "nestle",
        "Apollo",
        "bajaj",
        "asian",
        "icici",
        "ongc"
      ],
      "complex": [
        "jsw",
        "titan",
        "ADNA",
        "wipro",
        "ultratech",
        "infosys",
        "nestle",
        "Apollo",
        "bajaj",
        "asian",
        "icici",
        "ongc"
      ]
    },
    "long": {
      "simple": [
        "jsw",
        "titan",
        "ADNA",
        "wipro",
        "ultratech",
        "infosys",
        "nestle",
        "Apollo",
        "bajaj",
        "asian",
        "icici",
        "ongc"
      ],
      "medium": [
        "jsw",
        "titan",
        "ADNA",
        "wipro",
        "ultratech",
        "infosys",
        "nestle",
        "Apollo",
        "bajaj",
        "asian",
        "icici",
        "ongc"
      ],
      "complex": [
        "jsw",
        "titan",
        "ADNA",
        "wipro",
        "ultratech",
        "infosys",
        "nestle",
        "Apollo",
        "bajaj",
        "asian",
        "icici",
        "ongc"
      ]
    }
  },
  "timeframes": {
    "short": {
      "sequence_length": 30,
      "prediction_horizons": [
        1,
        3,
        5
      ]
    },
    "medium": {
      "sequence_length": 60,
      "prediction_horizons": [
        7,
        14,
        21
      ]
    },
    "long": {
      "sequence_length": 90,
      "prediction_horizons": [
        30,
        60,
        90
      ]
    }
  },
  "total_models_trained": 108
}